good_object_storage/__init__.py
good_object_storage/_client.py
good_object_storage-0.2.2.dist-info/METADATA
good_object_storage-0.2.2.dist-info/WHEEL
good_object_storage-0.2.2.dist-info/RECORD
