Metadata-Version: 2.4
Name: good-object-storage
Version: 0.2.2
Summary: Basic S3 client with some helpful utilities
Author-email: Chris Goddard <chris@goodkiwi.llc>
Requires-Python: >=3.12
Requires-Dist: aioboto3
Requires-Dist: b2sdk
Requires-Dist: good-common
Requires-Dist: msgpack
Requires-Dist: types-aiobotocore-s3
Requires-Dist: xxhash
